kusho_cli/__init__.py
kusho_cli/cli.py
kusho_cli-0.1.4.dist-info/LICENSE
kusho_cli-0.1.4.dist-info/METADATA
kusho_cli-0.1.4.dist-info/WHEEL
kusho_cli-0.1.4.dist-info/entry_points.txt
kusho_cli-0.1.4.dist-info/top_level.txt
kusho_cli-0.1.4.dist-info/RECORD
