Metadata-Version: 2.1
Name: kusho-cli
Version: 0.1.4
Summary: A CLI tool for generating and executing API test cases
Home-page: https://github.com/kusho-co/pip-kusho-cli
Author: KushoAI
Author-email: support@kusho.ai
Project-URL: Bug Tracker, https://github.com/kusho-co/pip-kusho-cli/issues
Classifier: Programming Language :: Python :: 3
Classifier: License :: OSI Approved :: MIT License
Classifier: Operating System :: OS Independent
Requires-Python: >=3.6
License-File: LICENSE
